[
  {
    "id": "735c1de1d674",
    "title": "My 2019 Annual Review",
    "url": "https://jamesclear.com/2019-annual-review",
    "source_id": "james_clear",
    "source_name": "James Clear",
    "platform": "James Clear",
    "category": "个人成长",
    "crawl_time": "2026-02-21 19:51:54",
    "crawl_date": "2026-02-21",
    "pub_time": null
  },
  {
    "id": "dc1708f59739",
    "title": "Happy 1st Birthday, Atomic Habits! (plus 3 gifts for you&#8230;)",
    "url": "https://jamesclear.com/atomic-habits-first-birthday",
    "source_id": "james_clear",
    "source_name": "James Clear",
    "platform": "James Clear",
    "category": "个人成长",
    "crawl_time": "2026-02-21 19:51:54",
    "crawl_date": "2026-02-21",
    "pub_time": null
  },
  {
    "id": "a278a7a40f10",
    "title": "The Ultimate Productivity Hack is Saying No",
    "url": "https://jamesclear.com/saying-no",
    "source_id": "james_clear",
    "source_name": "James Clear",
    "platform": "James Clear",
    "category": "个人成长",
    "crawl_time": "2026-02-21 19:51:54",
    "crawl_date": "2026-02-21",
    "pub_time": null
  },
  {
    "id": "7fc6661cc6eb",
    "title": "30 One-Sentence Stories From People Who Have Built Better Habits",
    "url": "https://jamesclear.com/one-sentence-habits",
    "source_id": "james_clear",
    "source_name": "James Clear",
    "platform": "James Clear",
    "category": "个人成长",
    "crawl_time": "2026-02-21 19:51:54",
    "crawl_date": "2026-02-21",
    "pub_time": null
  },
  {
    "id": "f1459478480f",
    "title": "The Ultimate Habit Tracker Guide: Why and How to Track Your Habits",
    "url": "https://jamesclear.com/habit-tracker",
    "source_id": "james_clear",
    "source_name": "James Clear",
    "platform": "James Clear",
    "category": "个人成长",
    "crawl_time": "2026-02-21 19:51:54",
    "crawl_date": "2026-02-21",
    "pub_time": null
  },
  {
    "id": "9f0b14a5f0e0",
    "title": "The Surprising Benefits of Journaling One Sentence Every Day",
    "url": "https://jamesclear.com/journaling-one-sentence",
    "source_id": "james_clear",
    "source_name": "James Clear",
    "platform": "James Clear",
    "category": "个人成长",
    "crawl_time": "2026-02-21 19:51:54",
    "crawl_date": "2026-02-21",
    "pub_time": null
  },
  {
    "id": "4a02509978da",
    "title": "My 2018 Annual Review",
    "url": "https://jamesclear.com/2018-annual-review",
    "source_id": "james_clear",
    "source_name": "James Clear",
    "platform": "James Clear",
    "category": "个人成长",
    "crawl_time": "2026-02-21 19:51:54",
    "crawl_date": "2026-02-21",
    "pub_time": null
  },
  {
    "id": "31305e9deb86",
    "title": "How to Make Your Future Habits Easy",
    "url": "https://jamesclear.com/reset-the-room",
    "source_id": "james_clear",
    "source_name": "James Clear",
    "platform": "James Clear",
    "category": "个人成长",
    "crawl_time": "2026-02-21 19:51:54",
    "crawl_date": "2026-02-21",
    "pub_time": null
  },
  {
    "id": "f8c390f77ceb",
    "title": "The Habits Scorecard: Use This Simple Exercise to Discover Which Habits You Should Change",
    "url": "https://jamesclear.com/habits-scorecard",
    "source_id": "james_clear",
    "source_name": "James Clear",
    "platform": "James Clear",
    "category": "个人成长",
    "crawl_time": "2026-02-21 19:51:54",
    "crawl_date": "2026-02-21",
    "pub_time": null
  },
  {
    "id": "e563c44d347a",
    "title": "When the 80/20 Rule Fails: The Downside of Being Effective",
    "url": "https://jamesclear.com/the-downside-of-being-effective",
    "source_id": "james_clear",
    "source_name": "James Clear",
    "platform": "James Clear",
    "category": "个人成长",
    "crawl_time": "2026-02-21 19:51:54",
    "crawl_date": "2026-02-21",
    "pub_time": null
  }
]